couchdblogger.py
__init__.py
couchdblogger-0.0.9.dist-info/RECORD
couchdblogger-0.0.9.dist-info/top_level.txt
couchdblogger-0.0.9.dist-info/metadata.json
couchdblogger-0.0.9.dist-info/METADATA
couchdblogger-0.0.9.dist-info/WHEEL
couchdblogger-0.0.9.dist-info/DESCRIPTION.rst
