Metadata-Version: 2.0
Name: couchdblogger
Version: 0.0.9
Summary: Simple module for logging to CouchDB.
Requires-Dist: requests
